ICARUS/CLOCK/pic16f84_clock.v
// Automatically generated .v file on Mon Nov 18 14:49:02 2024
//

module pic16f84_clock ( clk, vdd, vss, mclr, q1, q2, q3, q4, clk_out ) ;
   input wire [0:0] clk;
   input wire [3:0] vdd;
   input wire [3:0] vss;
   input wire [0:0] mclr;
   output reg [0:0] q1;
   output reg [0:0] q2;
   output reg [0:0] q3;
   output reg [0:0] q4;
   output reg [0:0] clk_out;

   // Implement the module here
   reg [1:0] phase_counter = 2'b00;

   // Initialize or reset the phase counter and outputs
always @(posedge clk) begin
   // if VSS is 2.0V - 6.0V and VSS is 0V
   if ((vdd <= 4'b0110 && vdd >= 4'b0010) && vss == 4'b0000 ) begin
      // resets if mclr is active low
      if (!mclr) begin
        phase_counter <= 2'b00;
        q1 <= 1'b0;
        q2 <= 1'b0;
        q3 <= 1'b0;
        q4 <= 1'b0;
        clk_out <= 1'b0;
      end
      else begin
         case (phase_counter)
            2'b00: begin
               q1 <= 1'b1;
               q2 <= 1'b0;
               q3 <= 1'b0;
               q4 <= 1'b0;
               clk_out <= 1'b0;
            end
            2'b01: begin
               q1 <= 1'b0;
               q2 <= 1'b1;
               q3 <= 1'b0;
               q4 <= 1'b0;
               clk_out <= 1'b0;
            end
            2'b10: begin
               q1 <= 1'b0;
               q2 <= 1'b0;
               q3 <= 1'b1;
               q4 <= 1'b0;
               clk_out <= 1'b1;
            end
            2'b11: begin
               q1 <= 1'b0;
               q2 <= 1'b0;
               q3 <= 1'b0;
               q4 <= 1'b1;
               clk_out <= 1'b1;
            end
         endcase
         phase_counter <= phase_counter + 1'b1;
      end
   end
   else begin
      phase_counter <= 2'b00;
      q1 <= 1'b0;
      q2 <= 1'b0;
      q3 <= 1'b0;
      q4 <= 1'b0;
      clk_out <= 1'b0;
   end

end

endmodule

ICARUS/CLOCK-(For Present)/pic16f84_clock_tb.v
`include "pic16f84_clock.v"


module pic16f84_clock_tb;

    reg [0:0] clk;
    reg [3:0] vdd;
    reg [3:0] vss;
    reg [0:0] mclr;
    wire [0:0] q1;
    wire [0:0] q2;
    wire [0:0] q3;
    wire [0:0] q4;
    wire [0:0] clk_out;

    pic16f84_clock uut (
    .clk(clk),
    .vdd(vdd),
    .vss(vss),
    .mclr(mclr),
    .q1(q1),
    .q2(q2),
    .q3(q3),
    .q4(q4),
    .clk_out(clk_out) 
    );

    always begin
        #10 clk = ~clk; 
    end

    initial begin
        $dumpfile("pic16f84_clock_tb.vcd");
        $dumpvars(0, pic16f84_clock_tb);

        vdd = 4'h5;
        vss = 4'h0;
        mclr = 1;
        clk = 0;

        #35;
        mclr = 1;
        
        // #15;
        // mclr = 0;
        
        // #50;
        // mclr = 1;

        // Run the simulation for a few clock cycles
        #300;

        // End the simulation
        $finish;

    end
endmodule

ICARUS/CLOCK-(For Present)/pic16f84_clock_tb.vcd
$date
	Tue Mar 18 21:37:41 2025
$end
$version
	Icarus Verilog
$end
$timescale
	1s
$end
$scope module pic16f84_clock_tb $end
$var wire 1 ! q4 $end
$var wire 1 " q3 $end
$var wire 1 # q2 $end
$var wire 1 $ q1 $end
$var wire 1 % clk_out $end
$var reg 1 & clk $end
$var reg 1 ' mclr $end
$var reg 4 ( vdd [3:0] $end
$var reg 4 ) vss [3:0] $end
$scope module uut $end
$var wire 1 & clk $end
$var wire 1 ' mclr $end
$var wire 4 * vdd [3:0] $end
$var wire 4 + vss [3:0] $end
$var reg 1 % clk_out $end
$var reg 2 , phase_counter [1:0] $end
$var reg 1 $ q1 $end
$var reg 1 # q2 $end
$var reg 1 " q3 $end
$var reg 1 ! q4 $end
$upscope $end
$upscope $end
$enddefinitions $end
$comment Show the parameter values. $end
$dumpall
$end
#0
$dumpvars
b0 ,
b0 +
b101 *
b0 )
b101 (
1'
0&
x%
x$
x#
x"
x!
$end
#10
b1 ,
0%
0!
0"
0#
1$
1&
#20
0&
#30
b10 ,
1#
0$
1&
#40
0&
#50
b11 ,
1%
1"
0#
1&
#60
0&
#70
b0 ,
1!
0"
1&
#80
0&
#90
b1 ,
0%
0!
1$
1&
#100
0&
#110
b10 ,
1#
0$
1&
#120
0&
#130
b11 ,
1%
1"
0#
1&
#140
0&
#150
b0 ,
1!
0"
1&
#160
0&
#170
b1 ,
0%
0!
1$
1&
#180
0&
#190
b10 ,
1#
0$
1&
#200
0&
#210
b11 ,
1%
1"
0#
1&
#220
0&
#230
b0 ,
1!
0"
1&
#240
0&
#250
b1 ,
0%
0!
1$
1&
#260
0&
#270
b10 ,
1#
0$
1&
#280
0&
#290
b11 ,
1%
1"
0#
1&
#300
0&
#310
b0 ,
1!
0"
1&
#320
0&
#330
b1 ,
0%
0!
1$
1&
