ICARUS/ROM/pic16f84_x1_rom.v
// Automatically generated .v file on Fri Nov  8 12:42:20 2024
//

module pic16f84_x1_rom ( pc_in, q1, nop_in, inst ) ;
// You will probably want to flush out the nature of these port declarations:
   input wire [12:0] pc_in;
   input wire [0:0] q1;
   input wire [0:0] nop_in;
   output reg [13:0] inst;

   // Implement the module here
   integer fd;                  // File descriptor
   reg [7:0] line[0:127];       // Fixed-size reg array for storing the line
   reg [7:0] char_in;           // To store each character
   integer i;                   // Loop index
   integer j;
   integer k;
   integer count;

   reg [7:0] low_byte, upper_byte;
   reg [15:0] addr;            //register to hold the address
   reg [15:0] paddr;
   reg [3:0] data;
   reg [7:0] byte_count, record_type;

   // Implement the module here
   initial begin
      fd = $fopen("INVERT_INPUT.hex", "r");  // Open the file in read mode
    if (fd == 0) begin
      $display("Error: Could not open file.");
    end else begin
      // Read the file character-by-character
      while (!$feof(fd)) begin
        i = 0;
        // Loop to read a single line (up to the newline or EOF)
        char_in = $fgetc(fd);
        while (i < 128 && char_in != 8'h0A && char_in != 8'hFF) begin
          line[i] = char_in;  // Store the character in the array
          i = i + 1;
          char_in = $fgetc(fd);  // Read the next character
        end

        //Obtains the characters per line
        for (j = 0; j < i; j = j + 1) begin
          //GET BYTE COUNT
          if (j == 1) begin
            if(line[j] >= "A" && line[j] <= "F") begin
              byte_count [7:4] = line[j] + 9;
            end
            else begin
              byte_count [7:4] = line[j];
            end
          end
          else if (j == 2) begin
            if(line[j] >= "A" && line[j] <= "F") begin
              byte_count [3:0] = line[j] + 9;
            end
            else begin
              byte_count [3:0] = line[j];
            end
          end
          //GET ADDRESS
          else if (j == 3)begin
            if(line[j] >= "A" && line[j] <= "F") begin
              addr [15:12] = line[j] + 9;
            end
            else begin
              addr [15:12] = line[j];
            end
          end
          else if (j == 4)begin
            if(line[j] >= "A" && line[j] <= "F") begin
              addr [11:8] = line[j] + 9;
            end
            else begin
              addr [11:8] = line[j];
            end
          end
          else if (j == 5)begin
            if(line[j] >= "A" && line[j] <= "F") begin
              addr [7:4] = line[j] + 9;
            end
            else begin
              addr [7:4] = line[j];
            end
          end
          else if (j == 6)begin
            if(line[j] >= "A" && line[j] <= "F") begin
              addr [3:0] = line[j] + 9;
            end
            else begin
              addr [3:0] = line[j];
            end
          end
          //GET RECORD TYPE
          else if (j == 7)begin
            if(line[j] >= "A" && line[j] <= "F") begin
              record_type [7:4] = line[j] + 9;
            end
            else begin
              record_type [7:4] = line[j];
            end
          end
          else if (j == 8)begin
            if(line[j] >= "A" && line[j] <= "F") begin
              record_type [3:0] = line[j] + 9;
            end
            else begin
              record_type [3:0] = line[j];
            end
          end

        end

        // GET DATA
        if (record_type == 8'h00 && byte_count != 8'h00) begin
          paddr = addr/2;
          count = 0;
          //ACCESS ONE CHARACTER AT A TIME
          for (k = 9; k <= (byte_count*2)+8; k = k+1) begin
            if(line[k] >= "A" && line[k] <= "F") begin
              // SINCE "A" - "F" CHARACTERS HAVE A DECIMAL VALUE FROM 65-70
              // SO WE SUBTRACT IT WITH 55 TO GET THE VALUE OF HEX IN DECIMAL
              // EXAMPLE:
              //     "F"      = 70 in decimal
              //     70 - 55  = 15 in decimal
              //     15 in HEX would equate to F
              data = line[k] - 55;

            end
            else if (line[k] >= "0" && line[k] <= "9") begin
              // SINCE "0" - "9" CHARACTERS HAVE A DECIMAL VALUE FROM 48-57
              // SO WE SUBTRACT IT WITH 55 TO GET THE VALUE OF HEX IN DECIMAL
              // EXAMPLE:
              //     "9"      = 57 in decimal
              //     57 - 48  = 9 in decimal
              //     9 in HEX would equate to 9
              data = line[k] - 48;

            end

            // EXTRACTS THE UPPER BYTE AND LOWER BYTE OF THE 14-BIT INSTRUCTIONS
            if(count == 0) begin
              low_byte [7:4] = data;
              count = count + 1;
            end
            else if (count == 1) begin
              low_byte [3:0] = data;
              count = count + 1;
            end
            else if (count == 2) begin
              upper_byte [7:4] = data;
              count = count + 1;
            end
            else if (count == 3) begin
              upper_byte [3:0] = data;
              count = 0;
              prog_mem [paddr] = {upper_byte, low_byte};
              $display("progmem[%h] = %h", paddr, prog_mem[paddr]);
              paddr = paddr + 1'b1;
            end

          end

        end

        // Stop if EOF (8'hFF) is detected
        if (char_in == 8'hFF) begin
          //disable end_of_file;
        end
        //end_of_file: ;
      end

      $fclose(fd);  // Close the file
    end

  end

  reg [15:0] prog_mem [0:1023];
  reg [13:0] IR;


  always @(*) begin
      if (q1) begin
         IR = prog_mem[pc_in][13:0];

         if(nop_in != 1'b0) begin
            inst = prog_mem[pc_in - 1'b1][13:0];
         end
         else begin
            inst = 14'h0000;
         end

      end

   end




endmodule

ICARUS/ROM-(For Present)/pic16f84_x1_rom_tb.v
`include "pic16f84_x1_rom.v"

module pic16f84_x1_rom_tb;

    reg [0:0] q1;
    reg [12:0] pc_in;
    reg [0:0] nop_in;
    wire [13:0] inst;

pic16f84_x1_rom uut (
   .q1(q1),
   .pc_in(pc_in),
   .nop_in(nop_in),
   .inst(inst)
);

initial begin
    $dumpfile("pic16f84_x1_rom_tb.vcd");
    $dumpvars(0, pic16f84_x1_rom_tb);

    nop_in = 0;
    q1 = 0;
    #20;

//======1ST CYCLE=====================
    q1 = 1;
    pc_in = 13'h0000;
    #20;

    q1 = 0;
    #10;
    nop_in = 1;
    #10;
//======2ND CYCLE=====================
    q1 = 1;
    pc_in = 13'h0001;
    #20;

    q1 = 0;
    #10;
    nop_in = 0;
    #10;
//======3RD CYCLE=====================
    q1 = 1;
    pc_in = 13'h03FE;
    #20;

    q1 = 0;
    #10;
    nop_in = 1;
    #10;
//======4TH CYCLE=====================
    q1 = 1;
    pc_in = 13'h03FF;
    #20;

    q1 = 0;
    #10;
    nop_in = 1;
    #10;
//======5TH CYCLE=====================
    q1 = 1;
    pc_in = 13'h0400;
    #20;

    q1 = 0;
    #10;
    nop_in = 0;
    #10;
//======6TH CYCLE=====================
    q1 = 1;
    pc_in = 13'h03F1;
    #20;

    q1 = 0;
    #10;
    nop_in = 1;
    #10;
//======7TH CYCLE=====================
    q1 = 1;
    pc_in = 13'h03F2;
    #20;

    q1 = 0;
    #10;
    nop_in = 0;
    #10;
//======8TH CYCLE=====================
    q1 = 1;
    pc_in = 13'h03F3;
    #20;

    q1 = 0;
    #10;
    nop_in = 1;
    #10;
//======9TH CYCLE=====================
    q1 = 1;
    pc_in = 13'h03F4;
    #20;

    q1 = 0;
    #10;
    nop_in = 1;
    #10;



    q1 = 0;
    #30;

 $finish;

end

endmodule

ICARUS/ROM-(For Present)/pic16f84_x1_rom_tb.vcd
$date
	Sun Mar 16 17:27:09 2025
$end
$version
	Icarus Verilog
$end
$timescale
	1s
$end
$scope module pic16f84_x1_rom_tb $end
$var wire 14 ! inst [13:0] $end
$var reg 1 " nop_in $end
$var reg 13 # pc_in [12:0] $end
$var reg 1 $ q1 $end
$scope module uut $end
$var wire 1 " nop_in $end
$var wire 13 % pc_in [12:0] $end
$var wire 1 $ q1 $end
$var reg 14 & IR [13:0] $end
$var reg 16 ' addr [15:0] $end
$var reg 8 ( byte_count [7:0] $end
$var reg 8 ) char_in [7:0] $end
$var reg 4 * data [3:0] $end
$var reg 14 + inst [13:0] $end
$var reg 8 , low_byte [7:0] $end
$var reg 16 - paddr [15:0] $end
$var reg 8 . record_type [7:0] $end
$var reg 8 / upper_byte [7:0] $end
$var integer 32 0 count [31:0] $end
$var integer 32 1 fd [31:0] $end
$var integer 32 2 i [31:0] $end
$var integer 32 3 j [31:0] $end
$var integer 32 4 k [31:0] $end
$upscope $end
$upscope $end
$enddefinitions $end
$comment Show the parameter values. $end
$dumpall
$end
#0
$dumpvars
b100101 4
b0 3
b0 2
b10000000000000000000000000000011 1
b0 0
b101011 /
b1 .
b10000000000 -
b11110001 ,
bx +
b1011 *
b11111111 )
b0 (
b0 '
bx &
bx %
0$
bx #
0"
bx !
$end
#20
b0 !
b0 +
b10101111111110 &
b0 #
b0 %
1$
#40
0$
#50
1"
#60
b10101111111110 !
b10101111111110 +
bx &
b1 #
b1 %
1$
#80
0$
#90
0"
#100
b0 !
b0 +
b110000011 &
b1111111110 #
b1111111110 %
1$
#120
0$
#130
1"
#140
b110000011 !
b110000011 +
b10101111110001 &
b1111111111 #
b1111111111 %
1$
#160
0$
#180
b10101111110001 !
b10101111110001 +
bx &
b10000000000 #
b10000000000 %
1$
#200
0$
#210
0"
#220
b0 !
b0 +
b11000011111111 &
b1111110001 #
b1111110001 %
1$
#240
0$
#250
1"
#260
b11000011111111 !
b11000011111111 +
b1011010000011 &
b1111110010 #
b1111110010 %
1$
#280
0$
#290
0"
#300
b0 !
b0 +
b10000101 &
b1111110011 #
b1111110011 %
1$
#320
0$
#330
1"
#340
b10000101 !
b10000101 +
b110000110 &
b1111110100 #
b1111110100 %
1$
#360
0$
